MANIFEST.in
README.rst
setup.py
colorbox/__init__.py
colorbox/decorators.py
colorbox/static/css/colorbox.css
colorbox/static/css/images/border.png
colorbox/static/css/images/controls.png
colorbox/static/css/images/loading.gif
colorbox/static/css/images/loading_background.png
colorbox/static/css/images/overlay.png
colorbox/static/css/images/ie6/borderBottomCenter.png
colorbox/static/css/images/ie6/borderBottomLeft.png
colorbox/static/css/images/ie6/borderBottomRight.png
colorbox/static/css/images/ie6/borderMiddleLeft.png
colorbox/static/css/images/ie6/borderMiddleRight.png
colorbox/static/css/images/ie6/borderTopCenter.png
colorbox/static/css/images/ie6/borderTopLeft.png
colorbox/static/css/images/ie6/borderTopRight.png
colorbox/static/js/colorbox.coop.js
colorbox/static/js/jquery.colorbox-min.js
colorbox/static/js/jquery.form.js
colorbox/templates/colorbox/popup_form_base.html
coop_colorbox.egg-info/PKG-INFO
coop_colorbox.egg-info/SOURCES.txt
coop_colorbox.egg-info/dependency_links.txt
coop_colorbox.egg-info/not-zip-safe
coop_colorbox.egg-info/top_level.txt